{
    "dataRecepcion": {
        "fechaRecep": "15-11-2022 15:02",
        "usuarioRecep": "flebot1",
        "examenesRecep": [{
                "NM_EXA_LAB": "COLESTEROL",
                "CD_EXA_LAB": "308",
                "STATUS_TOMA": "",
                "FECHA_TOMA": "",
                "USR_TOMA": "",
                "STATUS_RECEP": "1",
                "FECHA_RECEP": "15-11-2022 11:57",
                "USR_RECEP": "",
                "customCheked": true
            },
            {
                "NM_EXA_LAB": "CISTATINA C",
                "CD_EXA_LAB": "303",
                "STATUS_TOMA": "",
                "FECHA_TOMA": "",
                "USR_TOMA": "",
                "STATUS_RECEP": "1",
                "FECHA_RECEP": "15-11-2022 15:02",
                "USR_RECEP": "",
                "customCheked": true
            },
            {
                "NM_EXA_LAB": "CREATININA",
                "CD_EXA_LAB": "313",
                "STATUS_TOMA": "",
                "FECHA_TOMA": "",
                "USR_TOMA": "",
                "STATUS_RECEP": "1",
                "FECHA_RECEP": "15-11-2022 15:02",
                "USR_RECEP": "",
                "customCheked": true
            },
            {
                "NM_EXA_LAB": "GLUCOSA",
                "CD_EXA_LAB": "332",
                "STATUS_TOMA": "",
                "FECHA_TOMA": "",
                "USR_TOMA": "",
                "STATUS_RECEP": "1",
                "FECHA_RECEP": "15-11-2022 15:02",
                "USR_RECEP": "",
                "customCheked": true
            },
            {
                "NM_EXA_LAB": "LIPASA",
                "CD_EXA_LAB": "345",
                "STATUS_TOMA": "",
                "FECHA_TOMA": "",
                "USR_TOMA": "",
                "STATUS_RECEP": "1",
                "FECHA_RECEP": "15-11-2022 15:02",
                "USR_RECEP": "",
                "customCheked": true
            },
            {
                "NM_EXA_LAB": "PROTEINA C",
                "CD_EXA_LAB": "208",
                "STATUS_TOMA": "",
                "FECHA_TOMA": "",
                "USR_TOMA": "",
                "STATUS_RECEP": "1",
                "FECHA_RECEP": "15-11-2022 15:02",
                "USR_RECEP": "",
                "customCheked": true
            }
        ],
        "insumosRecep": {
            "tuboLila": 0,
            "tuboRojo": 0,
            "tuboCeleste": 0,
            "tuboNegro": 0,
            "tuboVerde": 0,
            "gsav": 0,
            "hemocultivo": 0,
            "qtb": 0
        }
    }
}